{
  "db_name": "PostgreSQL",
  "query": "\n            SELECT enrichment_type, COUNT(*)::bigint as \"count!: i64\"\n            FROM reasoning.enrichments\n            GROUP BY enrichment_type\n            ORDER BY enrichment_type\n            ",
  "describe": {
    "columns": [
      {
        "ordinal": 0,
        "name": "enrichment_type",
        "type_info": "Text"
      },
      {
        "ordinal": 1,
        "name": "count!: i64",
        "type_info": "Int8"
      }
    ],
    "parameters": {
      "Left": []
    },
    "nullable": [
      false,
      null
    ]
  },
  "hash": "26e3627a5fcb78350f55d667655e570394fc4e547cf2169325e009a735073bf6"
}
