{
  "db_name": "PostgreSQL",
  "query": "\n            SELECT id, LOWER(email) as \"email!\"\n            FROM org.people\n            WHERE LOWER(email) = ANY($1)\n              AND active = true\n            ",
  "describe": {
    "columns": [
      {
        "ordinal": 0,
        "name": "id",
        "type_info": "Uuid"
      },
      {
        "ordinal": 1,
        "name": "email!",
        "type_info": "Text"
      }
    ],
    "parameters": {
      "Left": [
        "TextArray"
      ]
    },
    "nullable": [
      false,
      null
    ]
  },
  "hash": "7501ca088015c7d851c33ac01d850fa53508be43f0a680a07c025da77fee72b3"
}
